pollywog.py
setup.py
pollywog.egg-info/PKG-INFO
pollywog.egg-info/SOURCES.txt
pollywog.egg-info/dependency_links.txt
pollywog.egg-info/top_level.txt