Metadata-Version: 1.1
Name: pollywog
Version: 0.1.1
Summary: pollywog
Home-page: http://github.com/coleifer/pollywog/
Author: Charles Leifer
Author-email: coleifer@gmail.com
License: UNKNOWN
Platform: UNKNOWN
Classifier: Development Status :: 5 - Production/Stable
Classifier: Intended Audience :: Developers
Classifier: License :: OSI Approved :: MIT License
Classifier: Operating System :: OS Independent
Classifier: Programming Language :: Python
